pycufsm-0.1.7.dist-info/RECORD
pycufsm-0.1.7.dist-info/LICENSE
pycufsm-0.1.7.dist-info/METADATA
pycufsm-0.1.7.dist-info/WHEEL
pycufsm/helpers.py
pycufsm/plotters.py
pycufsm/analysis_c.cpython-312-x86_64-linux-gnu.so
pycufsm/analysis_c.pyx
pycufsm/__init__.py
pycufsm/cfsm.py
pycufsm/analysis_p.py
pycufsm/fsm.py
pycufsm/_version.py
pycufsm/types.py
pycufsm/analysis.py
pycufsm/preprocess.py
pycufsm/cutwp.py
pycufsm/py.typed
pycufsm/Jupyter_Notebooks/pyCUFSM_load_mat.ipynb
pycufsm/Jupyter_Notebooks/pyCUFSM_GUI.ipynb
pycufsm/Jupyter_Notebooks/gui_widgets.py
pycufsm/Jupyter_Notebooks/pyCUFSM.ipynb
pycufsm/Jupyter_Notebooks/Validation.ipynb
pycufsm/examples/example_2.py
pycufsm/examples/example_1.py
pycufsm/examples/example_1_new.py
