Metadata-Version: 2.1
Name: pycufsm
Version: 0.1.7
Summary: Python CUFSM (Constrained and Unconstrained Finite Strip Method)
Home-page: https://github.com/ClearCalcs/pyCUFSM
License: AFL-3.0
Keywords: FSM,finite strip,CUFSM,CFS,thin-walled,cold-formed steel,aluminium,structural engineering,structural analysis
Author: Brooks Smith
Author-email: smith120bh@gmail.com
Requires-Python: >=3.10
Classifier: Development Status :: 3 - Alpha
Classifier: Intended Audience :: Science/Research
Classifier: License :: OSI Approved :: Academic Free License (AFL)
Classifier: Operating System :: OS Independent
Classifier: Programming Language :: Python :: 3
Classifier: Programming Language :: Python :: 3.10
Classifier: Programming Language :: Python :: 3.11
Classifier: Programming Language :: Python :: 3.12
Classifier: Programming Language :: Python :: 3.13
Classifier: Topic :: Scientific/Engineering
Classifier: Topic :: Scientific/Engineering :: Physics
Classifier: Topic :: Software Development :: Libraries :: Python Modules
Provides-Extra: jupyter
Provides-Extra: plot
Requires-Dist: ipywidgets (>=8.0.0) ; extra == "jupyter"
Requires-Dist: matplotlib (>=3.2) ; extra == "plot" or extra == "jupyter"
Requires-Dist: numpy (>=1.23.5)
Requires-Dist: scipy (>=1.10.0)
Project-URL: Documentation, https://pycufsm.readthedocs.io
Project-URL: Repository, https://github.com/ClearCalcs/pyCUFSM
